{
    "timestamp": "2025-07-14T14:30:00",
    "feathers_capture": {
        "active_window": "VSCode - Samurai Bluebird",
        "keystrokes": 432,
        "screenshot_analysis": {
            "detected_text": ["Bluebird Kernel", "Tri-Agent Reasoning"],
            "image_emotions": ["calm", "focused"]
        },
        "app_activity": ["PyCharm", "Notion", "Terminal"]
    },
    "symbolic_tags": {
        "sovereignties": ["Connection"],
        "chakras": ["Root"],
        "context_domains": ["Creativity"]
    },
    "meta": {
        "emotional_resonance": ["focused", "intentional"],
        "batch_index": 1,
        "notes": "Seed batch for system training. Simulated passive input."
    }
}
